eb/__init__.py
eb/server.py
sample_web_extractor-0.1.1.dist-info/METADATA
sample_web_extractor-0.1.1.dist-info/WHEEL
sample_web_extractor-0.1.1.dist-info/entry_points.txt
sample_web_extractor-0.1.1.dist-info/top_level.txt
sample_web_extractor-0.1.1.dist-info/RECORD
